{"nodes": [{"id": "d_app_2026_phanvietweb_deploy_fix_repo_storefront_src_modules_layout_components_cart_dropdown_index_tsx", "label": "index.tsx", "file_type": "code", "source_file": "D:\\APP 2026\\phanvietweb\\_deploy_fix_repo\\storefront\\src\\modules\\layout\\components\\cart-dropdown\\index.tsx", "source_location": "L1"}, {"id": "cart_dropdown_index_fmtvnd", "label": "fmtVND()", "file_type": "code", "source_file": "D:\\APP 2026\\phanvietweb\\_deploy_fix_repo\\storefront\\src\\modules\\layout\\components\\cart-dropdown\\index.tsx", "source_location": "L12"}, {"id": "cart_dropdown_index_countdown", "label": "Countdown()", "file_type": "code", "source_file": "D:\\APP 2026\\phanvietweb\\_deploy_fix_repo\\storefront\\src\\modules\\layout\\components\\cart-dropdown\\index.tsx", "source_location": "L16"}, {"id": "cart_dropdown_index_cartdropdown", "label": "CartDropdown()", "file_type": "code", "source_file": "D:\\APP 2026\\phanvietweb\\_deploy_fix_repo\\storefront\\src\\modules\\layout\\components\\cart-dropdown\\index.tsx", "source_location": "L27"}], "edges": [{"source": "d_app_2026_phanvietweb_deploy_fix_repo_storefront_src_modules_layout_components_cart_dropdown_index_tsx", "target": "react", "relation": "imports_from", "context": "import", "confidence": "EXTRACTED", "source_file": "D:\\APP 2026\\phanvietweb\\_deploy_fix_repo\\storefront\\src\\modules\\layout\\components\\cart-dropdown\\index.tsx", "source_location": "L3", "weight": 1.0}, {"source": "d_app_2026_phanvietweb_deploy_fix_repo_storefront_src_modules_layout_components_cart_dropdown_index_tsx", "target": "navigation", "relation": "imports_from", "context": "import", "confidence": "EXTRACTED", "source_file": "D:\\APP 2026\\phanvietweb\\_deploy_fix_repo\\storefront\\src\\modules\\layout\\components\\cart-dropdown\\index.tsx", "source_location": "L4", "weight": 1.0}, {"source": "d_app_2026_phanvietweb_deploy_fix_repo_storefront_src_modules_layout_components_cart_dropdown_index_tsx", "target": "types", "relation": "imports_from", "context": "import", "confidence": "EXTRACTED", "source_file": "D:\\APP 2026\\phanvietweb\\_deploy_fix_repo\\storefront\\src\\modules\\layout\\components\\cart-dropdown\\index.tsx", "source_location": "L5", "weight": 1.0}, {"source": "d_app_2026_phanvietweb_deploy_fix_repo_storefront_src_modules_layout_components_cart_dropdown_index_tsx", "target": "d_app_2026_phanvietweb_deploy_fix_repo_storefront_lib_data_cart", "relation": "imports_from", "context": "import", "confidence": "EXTRACTED", "source_file": "D:\\APP 2026\\phanvietweb\\_deploy_fix_repo\\storefront\\src\\modules\\layout\\components\\cart-dropdown\\index.tsx", "source_location": "L6", "weight": 1.0}, {"source": "d_app_2026_phanvietweb_deploy_fix_repo_storefront_src_modules_layout_components_cart_dropdown_index_tsx", "target": "data_cart_deletelineitem", "relation": "imports", "context": "import", "confidence": "EXTRACTED", "source_file": "D:\\APP 2026\\phanvietweb\\_deploy_fix_repo\\storefront\\src\\modules\\layout\\components\\cart-dropdown\\index.tsx", "source_location": "L6", "weight": 1.0}, {"source": "d_app_2026_phanvietweb_deploy_fix_repo_storefront_src_modules_layout_components_cart_dropdown_index_tsx", "target": "data_cart_applypromotions", "relation": "imports", "context": "import", "confidence": "EXTRACTED", "source_file": "D:\\APP 2026\\phanvietweb\\_deploy_fix_repo\\storefront\\src\\modules\\layout\\components\\cart-dropdown\\index.tsx", "source_location": "L6", "weight": 1.0}, {"source": "d_app_2026_phanvietweb_deploy_fix_repo_storefront_src_modules_layout_components_cart_dropdown_index_tsx", "target": "d_app_2026_phanvietweb_deploy_fix_repo_storefront_modules_common_components_localized_client_link", "relation": "imports_from", "context": "import", "confidence": "EXTRACTED", "source_file": "D:\\APP 2026\\phanvietweb\\_deploy_fix_repo\\storefront\\src\\modules\\layout\\components\\cart-dropdown\\index.tsx", "source_location": "L7", "weight": 1.0}, {"source": "d_app_2026_phanvietweb_deploy_fix_repo_storefront_src_modules_layout_components_cart_dropdown_index_tsx", "target": "cart_dropdown_index_fmtvnd", "relation": "contains", "confidence": "EXTRACTED", "source_file": "D:\\APP 2026\\phanvietweb\\_deploy_fix_repo\\storefront\\src\\modules\\layout\\components\\cart-dropdown\\index.tsx", "source_location": "L12", "weight": 1.0}, {"source": "d_app_2026_phanvietweb_deploy_fix_repo_storefront_src_modules_layout_components_cart_dropdown_index_tsx", "target": "cart_dropdown_index_countdown", "relation": "contains", "confidence": "EXTRACTED", "source_file": "D:\\APP 2026\\phanvietweb\\_deploy_fix_repo\\storefront\\src\\modules\\layout\\components\\cart-dropdown\\index.tsx", "source_location": "L16", "weight": 1.0}, {"source": "d_app_2026_phanvietweb_deploy_fix_repo_storefront_src_modules_layout_components_cart_dropdown_index_tsx", "target": "cart_dropdown_index_cartdropdown", "relation": "contains", "confidence": "EXTRACTED", "source_file": "D:\\APP 2026\\phanvietweb\\_deploy_fix_repo\\storefront\\src\\modules\\layout\\components\\cart-dropdown\\index.tsx", "source_location": "L27", "weight": 1.0}, {"source": "cart_dropdown_index_cartdropdown", "target": "cart_dropdown_index_fmtvnd", "relation": "calls", "context": "call", "confidence": "EXTRACTED", "source_file": "D:\\APP 2026\\phanvietweb\\_deploy_fix_repo\\storefront\\src\\modules\\layout\\components\\cart-dropdown\\index.tsx", "source_location": "L487", "weight": 1.0}], "raw_calls": [{"caller_nid": "cart_dropdown_index_fmtvnd", "callee": "format", "is_member_call": true, "source_file": "D:\\APP 2026\\phanvietweb\\_deploy_fix_repo\\storefront\\src\\modules\\layout\\components\\cart-dropdown\\index.tsx", "source_location": "L13"}, {"caller_nid": "cart_dropdown_index_countdown", "callee": "useState", "is_member_call": false, "source_file": "D:\\APP 2026\\phanvietweb\\_deploy_fix_repo\\storefront\\src\\modules\\layout\\components\\cart-dropdown\\index.tsx", "source_location": "L17"}, {"caller_nid": "cart_dropdown_index_countdown", "callee": "useEffect", "is_member_call": false, "source_file": "D:\\APP 2026\\phanvietweb\\_deploy_fix_repo\\storefront\\src\\modules\\layout\\components\\cart-dropdown\\index.tsx", "source_location": "L18"}, {"caller_nid": "cart_dropdown_index_countdown", "callee": "padStart", "is_member_call": true, "source_file": "D:\\APP 2026\\phanvietweb\\_deploy_fix_repo\\storefront\\src\\modules\\layout\\components\\cart-dropdown\\index.tsx", "source_location": "L22"}, {"caller_nid": "cart_dropdown_index_countdown", "callee": "String", "is_member_call": false, "source_file": "D:\\APP 2026\\phanvietweb\\_deploy_fix_repo\\storefront\\src\\modules\\layout\\components\\cart-dropdown\\index.tsx", "source_location": "L22"}, {"caller_nid": "cart_dropdown_index_countdown", "callee": "floor", "is_member_call": true, "source_file": "D:\\APP 2026\\phanvietweb\\_deploy_fix_repo\\storefront\\src\\modules\\layout\\components\\cart-dropdown\\index.tsx", "source_location": "L22"}, {"caller_nid": "cart_dropdown_index_countdown", "callee": "padStart", "is_member_call": true, "source_file": "D:\\APP 2026\\phanvietweb\\_deploy_fix_repo\\storefront\\src\\modules\\layout\\components\\cart-dropdown\\index.tsx", "source_location": "L23"}, {"caller_nid": "cart_dropdown_index_countdown", "callee": "String", "is_member_call": false, "source_file": "D:\\APP 2026\\phanvietweb\\_deploy_fix_repo\\storefront\\src\\modules\\layout\\components\\cart-dropdown\\index.tsx", "source_location": "L23"}, {"caller_nid": "cart_dropdown_index_cartdropdown", "callee": "useState", "is_member_call": false, "source_file": "D:\\APP 2026\\phanvietweb\\_deploy_fix_repo\\storefront\\src\\modules\\layout\\components\\cart-dropdown\\index.tsx", "source_location": "L28"}, {"caller_nid": "cart_dropdown_index_cartdropdown", "callee": "useState", "is_member_call": false, "source_file": "D:\\APP 2026\\phanvietweb\\_deploy_fix_repo\\storefront\\src\\modules\\layout\\components\\cart-dropdown\\index.tsx", "source_location": "L29"}, {"caller_nid": "cart_dropdown_index_cartdropdown", "callee": "useState", "is_member_call": false, "source_file": "D:\\APP 2026\\phanvietweb\\_deploy_fix_repo\\storefront\\src\\modules\\layout\\components\\cart-dropdown\\index.tsx", "source_location": "L30"}, {"caller_nid": "cart_dropdown_index_cartdropdown", "callee": "useState", "is_member_call": false, "source_file": "D:\\APP 2026\\phanvietweb\\_deploy_fix_repo\\storefront\\src\\modules\\layout\\components\\cart-dropdown\\index.tsx", "source_location": "L31"}, {"caller_nid": "cart_dropdown_index_cartdropdown", "callee": "useState", "is_member_call": false, "source_file": "D:\\APP 2026\\phanvietweb\\_deploy_fix_repo\\storefront\\src\\modules\\layout\\components\\cart-dropdown\\index.tsx", "source_location": "L33"}, {"caller_nid": "cart_dropdown_index_cartdropdown", "callee": "useRef", "is_member_call": false, "source_file": "D:\\APP 2026\\phanvietweb\\_deploy_fix_repo\\storefront\\src\\modules\\layout\\components\\cart-dropdown\\index.tsx", "source_location": "L34"}, {"caller_nid": "cart_dropdown_index_cartdropdown", "callee": "usePathname", "is_member_call": false, "source_file": "D:\\APP 2026\\phanvietweb\\_deploy_fix_repo\\storefront\\src\\modules\\layout\\components\\cart-dropdown\\index.tsx", "source_location": "L35"}, {"caller_nid": "cart_dropdown_index_cartdropdown", "callee": "useRouter", "is_member_call": false, "source_file": "D:\\APP 2026\\phanvietweb\\_deploy_fix_repo\\storefront\\src\\modules\\layout\\components\\cart-dropdown\\index.tsx", "source_location": "L36"}, {"caller_nid": "cart_dropdown_index_cartdropdown", "callee": "useEffect", "is_member_call": false, "source_file": "D:\\APP 2026\\phanvietweb\\_deploy_fix_repo\\storefront\\src\\modules\\layout\\components\\cart-dropdown\\index.tsx", "source_location": "L39"}, {"caller_nid": "cart_dropdown_index_cartdropdown", "callee": "reduce", "is_member_call": true, "source_file": "D:\\APP 2026\\phanvietweb\\_deploy_fix_repo\\storefront\\src\\modules\\layout\\components\\cart-dropdown\\index.tsx", "source_location": "L47"}, {"caller_nid": "cart_dropdown_index_cartdropdown", "callee": "reduce", "is_member_call": true, "source_file": "D:\\APP 2026\\phanvietweb\\_deploy_fix_repo\\storefront\\src\\modules\\layout\\components\\cart-dropdown\\index.tsx", "source_location": "L51"}, {"caller_nid": "cart_dropdown_index_cartdropdown", "callee": "reduce", "is_member_call": true, "source_file": "D:\\APP 2026\\phanvietweb\\_deploy_fix_repo\\storefront\\src\\modules\\layout\\components\\cart-dropdown\\index.tsx", "source_location": "L55"}, {"caller_nid": "cart_dropdown_index_cartdropdown", "callee": "useEffect", "is_member_call": false, "source_file": "D:\\APP 2026\\phanvietweb\\_deploy_fix_repo\\storefront\\src\\modules\\layout\\components\\cart-dropdown\\index.tsx", "source_location": "L63"}, {"caller_nid": "cart_dropdown_index_cartdropdown", "callee": "sort", "is_member_call": true, "source_file": "D:\\APP 2026\\phanvietweb\\_deploy_fix_repo\\storefront\\src\\modules\\layout\\components\\cart-dropdown\\index.tsx", "source_location": "L178"}, {"caller_nid": "cart_dropdown_index_cartdropdown", "callee": "map", "is_member_call": true, "source_file": "D:\\APP 2026\\phanvietweb\\_deploy_fix_repo\\storefront\\src\\modules\\layout\\components\\cart-dropdown\\index.tsx", "source_location": "L354"}]}