{"nodes": [{"id": "d_app_2026_phanvietweb_deploy_fix_repo_storefront_e2e_fixtures_account_overview_page_ts", "label": "overview-page.ts", "file_type": "code", "source_file": "D:\\APP 2026\\phanvietweb\\_deploy_fix_repo\\storefront\\e2e\\fixtures\\account\\overview-page.ts", "source_location": "L1"}, {"id": "account_overview_page_overviewpage", "label": "OverviewPage", "file_type": "code", "source_file": "D:\\APP 2026\\phanvietweb\\_deploy_fix_repo\\storefront\\e2e\\fixtures\\account\\overview-page.ts", "source_location": "L4"}, {"id": "account_overview_page_overviewpage_constructor", "label": ".constructor()", "file_type": "code", "source_file": "D:\\APP 2026\\phanvietweb\\_deploy_fix_repo\\storefront\\e2e\\fixtures\\account\\overview-page.ts", "source_location": "L14"}, {"id": "account_overview_page_overviewpage_getorder", "label": ".getOrder()", "file_type": "code", "source_file": "D:\\APP 2026\\phanvietweb\\_deploy_fix_repo\\storefront\\e2e\\fixtures\\account\\overview-page.ts", "source_location": "L28"}, {"id": "account_overview_page_overviewpage_goto", "label": ".goto()", "file_type": "code", "source_file": "D:\\APP 2026\\phanvietweb\\_deploy_fix_repo\\storefront\\e2e\\fixtures\\account\\overview-page.ts", "source_location": "L42"}], "edges": [{"source": "d_app_2026_phanvietweb_deploy_fix_repo_storefront_e2e_fixtures_account_overview_page_ts", "target": "test", "relation": "imports_from", "context": "import", "confidence": "EXTRACTED", "source_file": "D:\\APP 2026\\phanvietweb\\_deploy_fix_repo\\storefront\\e2e\\fixtures\\account\\overview-page.ts", "source_location": "L1", "weight": 1.0}, {"source": "d_app_2026_phanvietweb_deploy_fix_repo_storefront_e2e_fixtures_account_overview_page_ts", "target": "d_app_2026_phanvietweb_deploy_fix_repo_storefront_e2e_fixtures_account_account_page_ts", "relation": "imports_from", "context": "import", "confidence": "EXTRACTED", "source_file": "D:\\APP 2026\\phanvietweb\\_deploy_fix_repo\\storefront\\e2e\\fixtures\\account\\overview-page.ts", "source_location": "L2", "weight": 1.0}, {"source": "d_app_2026_phanvietweb_deploy_fix_repo_storefront_e2e_fixtures_account_overview_page_ts", "target": "account_account_page_accountpage", "relation": "imports", "context": "import", "confidence": "EXTRACTED", "source_file": "D:\\APP 2026\\phanvietweb\\_deploy_fix_repo\\storefront\\e2e\\fixtures\\account\\overview-page.ts", "source_location": "L2", "weight": 1.0}, {"source": "d_app_2026_phanvietweb_deploy_fix_repo_storefront_e2e_fixtures_account_overview_page_ts", "target": "account_overview_page_overviewpage", "relation": "contains", "confidence": "EXTRACTED", "source_file": "D:\\APP 2026\\phanvietweb\\_deploy_fix_repo\\storefront\\e2e\\fixtures\\account\\overview-page.ts", "source_location": "L4", "weight": 1.0}, {"source": "account_overview_page_overviewpage", "target": "account_overview_page_overviewpage_constructor", "relation": "method", "confidence": "EXTRACTED", "source_file": "D:\\APP 2026\\phanvietweb\\_deploy_fix_repo\\storefront\\e2e\\fixtures\\account\\overview-page.ts", "source_location": "L14", "weight": 1.0}, {"source": "account_overview_page_overviewpage", "target": "account_overview_page_overviewpage_getorder", "relation": "method", "confidence": "EXTRACTED", "source_file": "D:\\APP 2026\\phanvietweb\\_deploy_fix_repo\\storefront\\e2e\\fixtures\\account\\overview-page.ts", "source_location": "L28", "weight": 1.0}, {"source": "account_overview_page_overviewpage", "target": "account_overview_page_overviewpage_goto", "relation": "method", "confidence": "EXTRACTED", "source_file": "D:\\APP 2026\\phanvietweb\\_deploy_fix_repo\\storefront\\e2e\\fixtures\\account\\overview-page.ts", "source_location": "L42", "weight": 1.0}], "raw_calls": [{"caller_nid": "account_overview_page_overviewpage_constructor", "callee": "super", "is_member_call": false, "source_file": "D:\\APP 2026\\phanvietweb\\_deploy_fix_repo\\storefront\\e2e\\fixtures\\account\\overview-page.ts", "source_location": "L15"}, {"caller_nid": "account_overview_page_overviewpage_constructor", "callee": "getByTestId", "is_member_call": true, "source_file": "D:\\APP 2026\\phanvietweb\\_deploy_fix_repo\\storefront\\e2e\\fixtures\\account\\overview-page.ts", "source_location": "L16"}, {"caller_nid": "account_overview_page_overviewpage_constructor", "callee": "getByTestId", "is_member_call": true, "source_file": "D:\\APP 2026\\phanvietweb\\_deploy_fix_repo\\storefront\\e2e\\fixtures\\account\\overview-page.ts", "source_location": "L17"}, {"caller_nid": "account_overview_page_overviewpage_constructor", "callee": "getByTestId", "is_member_call": true, "source_file": "D:\\APP 2026\\phanvietweb\\_deploy_fix_repo\\storefront\\e2e\\fixtures\\account\\overview-page.ts", "source_location": "L18"}, {"caller_nid": "account_overview_page_overviewpage_constructor", "callee": "getByTestId", "is_member_call": true, "source_file": "D:\\APP 2026\\phanvietweb\\_deploy_fix_repo\\storefront\\e2e\\fixtures\\account\\overview-page.ts", "source_location": "L19"}, {"caller_nid": "account_overview_page_overviewpage_constructor", "callee": "getByTestId", "is_member_call": true, "source_file": "D:\\APP 2026\\phanvietweb\\_deploy_fix_repo\\storefront\\e2e\\fixtures\\account\\overview-page.ts", "source_location": "L22"}, {"caller_nid": "account_overview_page_overviewpage_constructor", "callee": "getByTestId", "is_member_call": true, "source_file": "D:\\APP 2026\\phanvietweb\\_deploy_fix_repo\\storefront\\e2e\\fixtures\\account\\overview-page.ts", "source_location": "L23"}, {"caller_nid": "account_overview_page_overviewpage_constructor", "callee": "getByTestId", "is_member_call": true, "source_file": "D:\\APP 2026\\phanvietweb\\_deploy_fix_repo\\storefront\\e2e\\fixtures\\account\\overview-page.ts", "source_location": "L24"}, {"caller_nid": "account_overview_page_overviewpage_constructor", "callee": "getByTestId", "is_member_call": true, "source_file": "D:\\APP 2026\\phanvietweb\\_deploy_fix_repo\\storefront\\e2e\\fixtures\\account\\overview-page.ts", "source_location": "L25"}, {"caller_nid": "account_overview_page_overviewpage_getorder", "callee": "locator", "is_member_call": true, "source_file": "D:\\APP 2026\\phanvietweb\\_deploy_fix_repo\\storefront\\e2e\\fixtures\\account\\overview-page.ts", "source_location": "L29"}, {"caller_nid": "account_overview_page_overviewpage_getorder", "callee": "getAttribute", "is_member_call": true, "source_file": "D:\\APP 2026\\phanvietweb\\_deploy_fix_repo\\storefront\\e2e\\fixtures\\account\\overview-page.ts", "source_location": "L34"}, {"caller_nid": "account_overview_page_overviewpage_getorder", "callee": "getByTestId", "is_member_call": true, "source_file": "D:\\APP 2026\\phanvietweb\\_deploy_fix_repo\\storefront\\e2e\\fixtures\\account\\overview-page.ts", "source_location": "L35"}, {"caller_nid": "account_overview_page_overviewpage_getorder", "callee": "getAttribute", "is_member_call": true, "source_file": "D:\\APP 2026\\phanvietweb\\_deploy_fix_repo\\storefront\\e2e\\fixtures\\account\\overview-page.ts", "source_location": "L36"}, {"caller_nid": "account_overview_page_overviewpage_getorder", "callee": "getByTestId", "is_member_call": true, "source_file": "D:\\APP 2026\\phanvietweb\\_deploy_fix_repo\\storefront\\e2e\\fixtures\\account\\overview-page.ts", "source_location": "L36"}, {"caller_nid": "account_overview_page_overviewpage_getorder", "callee": "textContent", "is_member_call": true, "source_file": "D:\\APP 2026\\phanvietweb\\_deploy_fix_repo\\storefront\\e2e\\fixtures\\account\\overview-page.ts", "source_location": "L37"}, {"caller_nid": "account_overview_page_overviewpage_getorder", "callee": "getByTestId", "is_member_call": true, "source_file": "D:\\APP 2026\\phanvietweb\\_deploy_fix_repo\\storefront\\e2e\\fixtures\\account\\overview-page.ts", "source_location": "L37"}, {"caller_nid": "account_overview_page_overviewpage_getorder", "callee": "getByTestId", "is_member_call": true, "source_file": "D:\\APP 2026\\phanvietweb\\_deploy_fix_repo\\storefront\\e2e\\fixtures\\account\\overview-page.ts", "source_location": "L38"}, {"caller_nid": "account_overview_page_overviewpage_goto", "callee": "click", "is_member_call": true, "source_file": "D:\\APP 2026\\phanvietweb\\_deploy_fix_repo\\storefront\\e2e\\fixtures\\account\\overview-page.ts", "source_location": "L43"}, {"caller_nid": "account_overview_page_overviewpage_goto", "callee": "waitFor", "is_member_call": true, "source_file": "D:\\APP 2026\\phanvietweb\\_deploy_fix_repo\\storefront\\e2e\\fixtures\\account\\overview-page.ts", "source_location": "L44"}]}